
{
  "banner1": {
    "comp": "Banner",
    "template": "banner",
    "left_editor": "LeftPanelBanner",
    "name": "BANNER",
    "style": {
      "width": "100%"
    },
    "content": {
      "link_address": "https://www.baidu.com",
      "img_address": "https://gw.alipayobjects.com/zos/rmsportal/nKBqduiIsQWrHPVehZrG.png"
    },
    "extends": {
      "title": "非通栏 Banner - 1",
      "img": "https://two.luoqintai.cn/uploads/2021/upload_44679e596ba8fdf2da634760ffb86f77.png"
    }
  },
  "carousel2": {
    "comp": "Carousel",
    "template": "carousel2",
    "left_editor": "LeftPanelCarousel",
    "name": "BANNER",
    "style": {
      "width": "100%"
    },
    "content": [
      {
        "link_address": "https://www.baidu.com",
        "img_address": "https://gw.alipayobjects.com/zos/rmsportal/nKBqduiIsQWrHPVehZrG.png"
      },
      {
        "link_address": "https://www.baidu.com",
        "img_address": "https://gw.alipayobjects.com/zos/rmsportal/JRmzNcWymcwpVRSISlbM.png"
      },
      {
        "link_address": "https://www.baidu.com",
        "img_address": "https://gw.alipayobjects.com/zos/rmsportal/nKBqduiIsQWrHPVehZrG.png"
      },
      {
        "link_address": "https://www.baidu.com",
        "img_address": "https://gw.alipayobjects.com/zos/rmsportal/JRmzNcWymcwpVRSISlbM.png"
      }
    ],
    "extends": {
      "title": "自动轮播 Banner",
      "img": "https://two.luoqintai.cn/uploads/2021/upload_5d9ef7f6156438849c98e8d7c4431ba9.png"
    }
  },
  "btn1": {
    "comp": "ComButton",
    "left_editor": "LeftPanelBtn",
    "template": "btn1",
    "name": "按钮",
    "style": {
      "color": "#333"
    },
    "content": {
      "link_address": "https://www.baidu.com",
      "text": "提交"
    },
    "extends": {
      "title": "普通按钮",
      "img": "https://two.luoqintai.cn/uploads/2021/upload_707e3b8cd91edce3451a1624bf92723c.png"
    }
  },
  "btn2": {
    "comp": "ComButton",
    "left_editor": "LeftPanelBtn",
    "template": "btn2",
    "name": "按钮",
    "style": {
      "color": "#333"
    },
    "content": {
      "link_address": "https://www.baidu.com",
      "text": "提交"
    },
    "extends": {
      "title": "普通吸底按钮",
      "img": "https://two.luoqintai.cn/uploads/2021/upload_3769d4f79fcbcf33eb8ea2cefbd37b47.png"
    }
  },
  "btn3": {
    "comp": "ComButton",
    "left_editor": "LeftPanelBtn",
    "template": "btn3",
    "name": "按钮",
    "style": {
      "color": "#333"
    },
    "content": {
      "link_address": "https://www.baidu.com",
      "text": "立即申请"
    },
    "extends": {
      "title": "通栏吸底按钮",
      "img": "https://two.luoqintai.cn/uploads/2021/upload_6e6a6405291f9414cc54737ce8355602.png"
    }
  },
  "faq1": {
    "comp": "ComFAQ",
    "left_editor": "LeftPanelFaq",
    "template": "faq1",
    "name": "FAQ",
    "style": {
      "color": "#333"
    },
    "content": {
      "title": "什么是可视化页面搭建？",
      "text": "<div>无需搭建开发环境和部署服务器，基于开发者工具，使用丰富的 UI 组件和行业模板研发 H5 站点，2 分钟完成站点部署。</div>"
    },
    "extends": {
      "title": "普通 FAQ - 1",
      "img": "https://two.luoqintai.cn/uploads/2021/upload_af54d9eef612ac3473c4cf6446baeebc.png"
    }
  },
  "faq2": {
    "comp": "ComFAQ",
    "left_editor": "LeftPanelFaq",
    "template": "faq2",
    "name": "FAQ",
    "style": {
      "color": "#333"
    },
    "content": {
      "title": "什么是可视化页面搭建？",
      "text": "<div>无需搭建开发环境和部署服务器，基于开发者工具，使用丰富的 UI 组件和行业模板研发 H5 站点，2 分钟完成站点部署。</div>"
    },
    "extends": {
      "title": "普通 FAQ - 2",
      "img": "https://two.luoqintai.cn/uploads/2021/upload_c415a7c5ee12a57a221e05d5aa228544.png"
    }
  },
  "footer1": {
    "comp": "ComFooter",
    "left_editor": "LeftPanelFooter",
    "template": "footer1",
    "name": "页脚",
    "style": {
      "width": "100%"
    },
    "content": "https://gw.alipayobjects.com/zos/rmsportal/XtMFIqbtszjfPnrtQnIe.png",
    "extends": {
      "title": "图片页脚 - 1",
      "img": "https://two.luoqintai.cn/uploads/2021/upload_0965d2139df21b71543825ffea1a4307.png"
    }
  },
  "img1": {
    "comp": "ComImg",
    "left_editor": "LeftPanelImg",
    "template": "img1",
    "name": "配图",
    "style": {
      "width": "100%"
    },
    "content": {
      "link_address": "https://www.baidu.com",
      "img_address": "https://gw.alipayobjects.com/zos/rmsportal/hxisPCETBGwVXAdEYrke.png"
    },
    "extends": {
      "title": "配图 - 1",
      "img": "https://two.luoqintai.cn/uploads/2021/upload_7dc5a12625803da38d8f06561fcc873b.png"
    }
  },
  "img2": {
    "comp": "ComImg",
    "left_editor": "LeftPanelImg",
    "template": "img2",
    "name": "配图",
    "style": {
      "width": "100%"
    },
    "content": {
      "link_address": "https://www.baidu.com",
      "img_address": "https://gw.alipayobjects.com/zos/rmsportal/hxisPCETBGwVXAdEYrke.png",
      "desc": "产品图"
    },
    "extends": {
      "title": "配图 - 2（带标注）",
      "img": "https://two.luoqintai.cn/uploads/2021/upload_4dc8525a42081eab568fc5c9d470abcb.png"
    }
  },
  "step1": {
    "comp": "ComStep",
    "left_editor": "LeftPanelStep",
    "template": "step1",
    "name": "步骤",
    "style": {
      "color": "#333"
    },
    "content": [
      {
        "step": "Step 1",
        "title": "在线预定",
        "desc": "填写信息，上传驾照正反面",
        "img_address": "https://gw.alipayobjects.com/zos/rmsportal/ooZDRgfpKxPsQSrVmGZX.png"
      },
      {
        "step": "Step 2",
        "title": "翻译制作",
        "desc": "对驾照信息进行翻译及认证，于 1 个工作日内完成",
        "img_address": "https://gw.alipayobjects.com/zos/rmsportal/XKTyAJMVsgjEOuxwtITN.png"
      },
      {
        "step": "Step 3",
        "title": "寄送到家",
        "desc": "在证件的最后一页贴上白底证件照，签署中文姓名",
        "img_address": "https://gw.alipayobjects.com/zos/rmsportal/QJXyJDFxUiHbSfShONXG.png"
      }
    ],
    "extends": {
      "title": "步骤 - 1",
      "img": "https://two.luoqintai.cn/uploads/2021/upload_48417812c3e65e77887ec6947a77b689.png"
    }
  },
  "step3": {
    "comp": "ComStep",
    "left_editor": "LeftPanelStep",
    "template": "step3",
    "name": "步骤",
    "style": {
      "color": "#333"
    },
    "content": [
      {
        "step": "Step 1",
        "title": "在线预定",
        "desc": "填写信息，上传驾照正反面",
        "img_address": "https://gw.alipayobjects.com/zos/rmsportal/oXWUFANYmciCOAAEQJjD.png"
      },
      {
        "step": "Step 2",
        "title": "翻译制作",
        "desc": "对驾照信息进行翻译及认证，于 1 个工作日内完成",
        "img_address": "https://gw.alipayobjects.com/zos/rmsportal/PeDRFGbGRbNBIaQTDndp.png"
      },
      {
        "step": "Step 3",
        "title": "寄送到家",
        "desc": "在证件的最后一页贴上白底证件照，签署中文姓名",
        "img_address": "https://gw.alipayobjects.com/zos/rmsportal/BepCpOQgGGMpWAJiPiYZ.png"
      }
    ],
    "extends": {
      "title": "步骤 - 3",
      "img": "https://two.luoqintai.cn/uploads/2021/upload_5882c03632a8c84aeb1245936bd7799e.png"
    }
  },
  "cutlist1": {
    "comp": "CutList",
    "left_editor": "LeftPanelCutList",
    "template": "cutlist1",
    "name": "列表",
    "style": {
      "color": "#333"
    },
    "content": {
      "title": "为什么这么多大企业都在做可视化页面搭建？",
      "img_address": "https://gw.alipayobjects.com/zos/rmsportal/ebuQSFOLCrYqpCHmfxll.png",
      "link_address": "https://www.baidu.com",
      "desc": "无需搭建开发环境和部署服务器，基于开发者工具，使用丰富的 UI 组件和行业模板研发 H5"
    },
    "extends": {
      "title": "资讯列表 - 左右布局 - 1 (带摘要)",
      "img": "https://two.luoqintai.cn/uploads/2021/upload_ada551c5b8bb1aa9a115a004a49f20c5.png"
    }
  },
  "cutlist2": {
    "comp": "CutList",
    "left_editor": "LeftPanelCutList",
    "template": "cutlist2",
    "name": "列表",
    "style": {
      "color": "#333"
    },
    "content": {
      "title": "为什么这么多大企业都在做可视化页面搭建？",
      "link_address": "https://www.baidu.com",
      "img_address": "https://gw.alipayobjects.com/zos/rmsportal/ebuQSFOLCrYqpCHmfxll.png"
    },
    "extends": {
      "title": "资讯列表 - 左右布局 - 2",
      "img": "https://two.luoqintai.cn/uploads/2021/upload_81cb156a8fd328d09a00672b0e8ecd7a.png"
    }
  },
  "gridlist3": {
    "comp": "GridList",
    "left_editor": "LeftPanelGridList",
    "template": "gridlist3",
    "name": "列表",
    "style": {
      "color": "#333"
    },
    "content": [
      {
        "children": [
          {
            "title": "海外旅行",
            "link_address": "https://www.baidu.com",
            "img_address": "https://gw.alipayobjects.com/zos/rmsportal/wWQZevyGptOADcEhscIp.png"
          },
          {
            "title": "出国留学",
            "link_address": "https://www.baidu.com",
            "img_address": "https://gw.alipayobjects.com/zos/rmsportal/YVtEOLbGeJXCFrOARpLS.png"
          },
          {
            "title": "留学快汇",
            "link_address": "https://www.baidu.com",
            "img_address": "https://gw.alipayobjects.com/zos/rmsportal/iHEPGHUfgKMuIJhnmYCk.png"
          }
        ]
      },
      {
        "children": [
          {
            "title": "商务出行",
            "link_address": "https://www.baidu.com",
            "img_address": "https://gw.alipayobjects.com/zos/rmsportal/VJeIDTUhhgZbEOAZcXeE.png"
          },
          {
            "title": "资产配置",
            "link_address": "https://www.baidu.com",
            "img_address": "https://gw.alipayobjects.com/zos/rmsportal/MsBVFalmPzPZWnovieJz.png"
          },
          {
            "title": "代办签证",
            "link_address": "https://www.baidu.com",
            "img_address": "https://gw.alipayobjects.com/zos/rmsportal/IJPHFytoWJjCBrKTQxhx.png"
          }
        ]
      }
    ],
    "extends": {
      "title": "网格列表 - 3",
      "img": "https://two.luoqintai.cn/uploads/2021/upload_5a914108183218db91bf84de0f9fadb9.png"
    }
  },
  "cardlist1": {
    "comp": "GridList2",
    "left_editor": "LeftPanelCardList",
    "template": "cardlist1",
    "name": "列表",
    "style": {
      "color": "#333"
    },
    "content": {
      "tag": "旅行",
      "title": "海外旅行",
      "link_address": "https://www.baidu.com",
      "subtitle": "多国特色签证",
      "img_address": "https://gw.alipayobjects.com/zos/rmsportal/uEzOwVPOgaIuMJUACDIg.png"
    },
    "extends": {
      "title": "卡片列表 - 1",
      "img": "https://two.luoqintai.cn/uploads/2021/upload_1bba24e10a41a775e88cb08483a45c11.png"
    }
  },
  "cardlist2": {
    "comp": "GridList2",
    "left_editor": "LeftPanelCardList",
    "template": "cardlist2",
    "name": "列表",
    "style": {
      "color": "#333"
    },
    "content": {
      "tag": "商务",
      "img_address": "https://gw.alipayobjects.com/os/q/cms/images/jnlh56kl/95765c17-d8b5-4e82-af96-f501ef35bacb.cms/images/5029657b-8a4d-48ba-bccd-55daa3c6d5a2.png?x-oss-process=image/resize,w_560/crop,h_560",
      "link_address": "https://www.baidu.com",
      "title": "商务出行",
      "subtitle": "出国工作安心无忧"
    },
    "extends": {
      "title": "卡片列表 - 2",
      "img": "https://two.luoqintai.cn/uploads/2021/upload_c601b61784e8eea85d15189afd163372.png"
    }
  },
  "gridlist1": {
    "comp": "GridList2",
    "left_editor": "LeftPanelGridList",
    "template": "gridlist1",
    "name": "列表",
    "style": {
      "color": "#333"
    },
    "content": [
      {
        "children": [
          {
            "title": "俄罗斯",
            "subtitle": "世界杯免签办理",
            "link_address": "https://www.baidu.com",
            "img_address": "https://gw.alipayobjects.com/zos/rmsportal/dGUxUULyLhgGvkwoNsHn.png"
          },
          {
            "title": "新西兰",
            "subtitle": "家庭签证",
            "link_address": "https://www.baidu.com",
            "img_address": "https://gw.alipayobjects.com/zos/rmsportal/rnLarHmjMpKasWVMFVnZ.png"
          }
        ]
      },
      {
        "children": [
          {
            "title": "马来西亚",
            "subtitle": "旅游电子签证",
            "link_address": "https://www.baidu.com",
            "img_address": "https://gw.alipayobjects.com/zos/rmsportal/ifSqazvXgwLdBYrWNFQk.png"
          },
          {
            "title": "日本",
            "subtitle": "签证快捷办理",
            "link_address": "https://www.baidu.com",
            "img_address": "https://gw.alipayobjects.com/zos/rmsportal/vXNwQdxjBZPdAMNaHiKy.png"
          }
        ]
      }
    ],
    "extends": {
      "title": "网格列表 - 1",
      "img": "https://two.luoqintai.cn/uploads/2021/upload_7f934e75731ddec6eed0a7d69d39ef6f.png"
    }
  },
  "gridlist2": {
    "comp": "GridList2",
    "left_editor": "LeftPanelGridList",
    "template": "gridlist2",
    "name": "列表",
    "style": {
      "color": "#333"
    },
    "content": [
      {
        "children": [
          {
            "title": "海外旅行",
            "subtitle": "多国特色签证",
            "tag": "旅行",
            "link_address": "https://www.baidu.com",
            "img_address": "https://gw.alipayobjects.com/zos/rmsportal/ZnGdPxoHrVXmGUqXouiU.png"
          },
          {
            "title": "出国留学",
            "subtitle": "全方位留学服务",
            "tag": "留学",
            "link_address": "https://www.baidu.com",
            "img_address": "https://gw.alipayobjects.com/zos/rmsportal/FpAKgrtDMKTXhIVdVfIj.png"
          }
        ]
      },
      {
        "children": [
          {
            "title": "商务出行",
            "subtitle": "出国工作安心无忧",
            "tag": "商务",
            "link_address": "https://www.baidu.com",
            "img_address": "https://gw.alipayobjects.com/zos/rmsportal/KmzovGuElReNFnhykhMf.png"
          },
          {
            "title": "资产配置",
            "subtitle": "沪港深基金连接境内外",
            "tag": "资产",
            "link_address": "https://www.baidu.com",
            "img_address": "https://gw.alipayobjects.com/zos/rmsportal/RfVtHjHOpezICADhNcxh.png"
          }
        ]
      }
    ],
    "extends": {
      "title": "网格列表 - 2",
      "img": "https://two.luoqintai.cn/uploads/2021/upload_5b16a607ec074605c77a219d8a3644db.png"
    }
  },
  "newlist3": {
    "comp": "NewList",
    "left_editor": "LeftPanelNewList",
    "template": "newlist3",
    "name": "列表",
    "style": {
      "color": "#333"
    },
    "content": {
      "title": "为什么这么多大企业都在做可视化页面搭建？",
      "img_address": [
        [
          "https://gw.alipayobjects.com/zos/rmsportal/QncRkuaOpqaYLBoxyEmW.png",
          "https://gw.alipayobjects.com/zos/rmsportal/idMzNdbVOavlarSCCWEL.png",
          "https://gw.alipayobjects.com/zos/rmsportal/PfeIDYodSsakxpFemfZd.png"
        ],
        [
          "https://gw.alipayobjects.com/zos/rmsportal/kLpVGRlmVkhSVpqyBxKj.png",
          "https://gw.alipayobjects.com/zos/rmsportal/gWYqjqJFBRTNhRNYrQkE.png",
          "https://gw.alipayobjects.com/zos/rmsportal/lKDrgTiyERvYSeMvdirE.png"
        ]
      ],
      "link_address": "https://www.baidu.com",
      "tag": [
        "市场",
        "第一财经"
      ]
    },
    "extends": {
      "title": "资讯列表 - 上下布局 - 3",
      "img": "https://two.luoqintai.cn/uploads/2021/upload_fd17f9e03e0195b2c097b39792908fa6.png"
    }
  },
  "normallist1": {
    "comp": "NormalList",
    "template": "normal1",
    "left_editor": "LeftPanelNormalList",
    "name": "列表",
    "style": {
      "color": "#333"
    },
    "content": {
      "link_address": "https://www.baidu.com",
      "title": "为什么这么多大企业都在做可视化页面搭建？",
      "tag": [
        "市场",
        "第一财经"
      ]
    },
    "extends": {
      "title": "普通列表 - 1",
      "img": "https://two.luoqintai.cn/uploads/2021/upload_f77cc04f4ad2f33238ee73c83d02e9b8.png"
    }
  },
  "normallist2": {
    "comp": "NormalList",
    "template": "normal2",
    "left_editor": "LeftPanelNormalList",
    "name": "列表",
    "style": {
      "color": "#333"
    },
    "content": {
      "link_address": "https://www.baidu.com",
      "title": "为什么这么多大企业都在做可视化页面搭建？",
      "img_address": "https://gw.alipayobjects.com/zos/rmsportal/ebuQSFOLCrYqpCHmfxll.png",
      "tag": [
        "市场",
        "第一财经"
      ]
    },
    "extends": {
      "title": "普通列表 - 2",
      "img": "https://two.luoqintai.cn/uploads/2021/upload_0994ec8570ce26cb281fd5f2db3c7a5c.png"
    }
  },
  "normallist3": {
    "comp": "NormalList",
    "template": "normal3",
    "left_editor": "LeftPanelNormalList",
    "name": "列表",
    "style": {
      "color": "#333"
    },
    "content": {
      "link_address": "https://www.baidu.com",
      "title": "为什么这么多大企业都在做可视化页面搭建？",
      "img_address": "https://gw.alipayobjects.com/zos/rmsportal/ebuQSFOLCrYqpCHmfxll.png",
      "tag": [
        "市场",
        "第一财经"
      ]
    },
    "extends": {
      "title": "普通列表 - 3",
      "img": "https://two.luoqintai.cn/uploads/2021/upload_ff4502b27a1f10e8d1d49c5d1b090f8c.png"
    }
  },
  "operationlist1": {
    "comp": "OperationList",
    "left_editor": "LeftPanelOperationList",
    "template": "opt1",
    "name": "列表",
    "style": {
      "color": "#333"
    },
    "content": {
      "title": "全栈工程师兼职",
      "tag": [
        "180元/小时",
        "日结"
      ],
      "area": "上城-区政府",
      "link_address": "https://www.baidu.com",
      "btn": "报名"
    },
    "extends": {
      "title": "带操作列表 - 1",
      "img": "https://two.luoqintai.cn/uploads/2021/upload_e16b4493b30d9441462fe7d5f2d4701d.png"
    }
  },
  "operationlist2": {
    "comp": "OperationList",
    "left_editor": "LeftPanelOperationList",
    "template": "opt2",
    "name": "列表",
    "style": {
      "color": "#333"
    },
    "content": {
      "title": "全栈工程师兼职",
      "tag": [
        "180元/小时",
        "日结"
      ],
      "area": "上城-区政府",
      "img_address": "https://gw.alipayobjects.com/zos/rmsportal/qnMZzTAViDGQHHjgyICm.png",
      "link_address": "https://www.baidu.com",
      "btn": "报名"
    },
    "extends": {
      "title": "带操作列表 - 2",
      "img": "https://two.luoqintai.cn/uploads/2021/upload_2c6353a4249bc7fab0bcd323551b2318.png"
    }
  },
  "detail3": {
    "comp": "Paragraph",
    "left_editor": "LeftPanelParleft",
    "template": "detail3",
    "name": "段落",
    "style": {
      "color": "#333"
    },
    "content": {
      "title": "体验技术部产品专家",
      "tag": [
        "10K/每月",
        "月结"
      ]
    },
    "extends": {
      "title": "文章标题 + 文章信息 - 3",
      "img": "https://two.luoqintai.cn/uploads/2021/upload_57289752957b6a09a78e73c38a924b8a.png"
    }
  },
  "parleft3": {
    "comp": "Paragraph",
    "left_editor": "LeftPanelParleft",
    "template": "parleft3",
    "name": "段落",
    "style": {
      "color": "#333"
    },
    "content": {
      "title": "标题",
      "text": "<div>1. 负责部门的产品规划、设计和产品生命周期管理；<br />2. 基于用户体验设计理念，结合用户需求和产品技术架构，完成产品/功能的概念设计和原型展示；</div>"
    },
    "extends": {
      "title": "小标题+正文 - 左对齐 - 3",
      "img": "https://two.luoqintai.cn/uploads/2021/upload_b2ff8af24671638c341220078f37f323.png"
    }
  },
  "quote1": {
    "comp": "Quote",
    "left_editor": "LeftPanelQuote",
    "template": "quote1",
    "name": "引言",
    "style": {
      "color": "#333"
    },
    "content": "云凤蝶的文化：客户第一，追求极致，勇于创新，开放共赢 / 云凤蝶的品牌定位：丰富、简单、个性、开放。",
    "extends": {
      "title": "引言 - 1",
      "img": "https://two.luoqintai.cn/uploads/2021/upload_df914dafa823667dd3e73abe850ecd55.png"
    }
  },
  "quote2": {
    "comp": "Quote",
    "left_editor": "LeftPanelQuote",
    "template": "quote2",
    "name": "引言",
    "style": {
      "color": "#333"
    },
    "content": "云凤蝶的文化：客户第一，追求极致，勇于创新，开放共赢 / 云凤蝶的品牌定位：丰富、简单、个性、开放。",
    "extends": {
      "title": "引言 - 2",
      "img": "https://two.luoqintai.cn/uploads/2021/upload_b2b91927421296951d4e2032129cb946.png"
    }
  },
  "rowlist1": {
    "comp": "RowList",
    "left_editor": "LeftPanelRowList",
    "template": "rowlist1",
    "name": "列表",
    "style": {
      "width": "100%"
    },
    "content": [
      {
        "link_address": "https://www.baidu.com",
        "img_address": "https://gw.alipayobjects.com/zos/rmsportal/qnMZzTAViDGQHHjgyICm.png",
        "title": "银行存款证明",
        "tag": "金融"
      },
      {
        "link_address": "https://www.baidu.com",
        "img_address": "https://gw.alipayobjects.com/zos/rmsportal/qnMZzTAViDGQHHjgyICm.png",
        "title": "全币种信用卡",
        "tag": "信用卡"
      }
    ],
    "extends": {
      "title": "纵向列表 - 1",
      "img": "https://two.luoqintai.cn/uploads/2021/upload_12d54cd8acb9ceff49847e78acac451b.png"
    }
  },
  "tab2": {
    "comp": "EntryTab",
    "template": "tab2",
    "left_editor": "LeftPanelTab2",
    "name": "TAB",
    "style": {
      "width": "100%"
    },
    "content": [
      {
        "label": "境外汇款",
        "img_address": "https://gw.alipayobjects.com/zos/rmsportal/AOtWvDPAJgtZPFMXHKNm.png",
        "link_address": "https://www.baidu.com"
      },
      {
        "label": "外汇结汇",
        "img_address": "https://gw.alipayobjects.com/zos/rmsportal/RgGGnFTIqGzkLIZyMFej.png",
        "link_address": "https://www.baidu.com"
      },
      {
        "label": "代理签证",
        "img_address": "https://gw.alipayobjects.com/zos/rmsportal/ycOPKaiWZFtKyhDCxRAY.png",
        "link_address": "https://www.baidu.com"
      },
      {
        "label": "国际机票",
        "img_address": "https://gw.alipayobjects.com/zos/rmsportal/oOhXrdlcKBHAPiEatqNR.png",
        "link_address": "https://www.baidu.com"
      }
    ],
    "extends": {
      "title": "普通功能入口 - 1",
      "img": "https://two.luoqintai.cn/uploads/2021/upload_5e1fbe8ff66d33429943d22403f2f336.png"
    }
  },
  "tab1": {
    "comp": "Tab",
    "template": "tab1",
    "left_editor": "LeftPanelTab1",
    "name": "TAB",
    "style": {
      "width": "100%"
    },
    "content": [
      {
        "label": "Tab 1",
        "children": [
          {
            "img_address": "https://gw.alipayobjects.com/zos/rmsportal/ebuQSFOLCrYqpCHmfxll.png",
            "title": "为什么这么多大企业都在做可视化页面搭建？",
            "link_address": "https://www.baidu.com"
          },
          {
            "img_address": "https://gw.alipayobjects.com/zos/rmsportal/ebuQSFOLCrYqpCHmfxll.png",
            "title": "为什么这么多大企业都在做可视化页面搭建？",
            "link_address": "https://www.baidu.com"
          }
        ]
      },
      {
        "label": "Tab 2",
        "children": [
          {
            "img_address": "https://gw.alipayobjects.com/zos/rmsportal/ebuQSFOLCrYqpCHmfxll.png",
            "title": "为什么这么多大企业都在做可视化页面搭建？",
            "link_address": "https://www.baidu.com"
          },
          {
            "img_address": "https://gw.alipayobjects.com/zos/rmsportal/ebuQSFOLCrYqpCHmfxll.png",
            "title": "为什么这么多大企业都在做可视化页面搭建？",
            "link_address": "https://www.baidu.com"
          }
        ]
      },
      {
        "label": "Tab 3",
        "children": [
          {
            "img_address": "https://gw.alipayobjects.com/zos/rmsportal/ebuQSFOLCrYqpCHmfxll.png",
            "title": "为什么这么多大企业都在做可视化页面搭建？",
            "link_address": "https://www.baidu.com"
          },
          {
            "img_address": "https://gw.alipayobjects.com/zos/rmsportal/ebuQSFOLCrYqpCHmfxll.png",
            "title": "为什么这么多大企业都在做可视化页面搭建？",
            "link_address": "https://www.baidu.com"
          }
        ]
      },
      {
        "label": "Tab 4",
        "children": [
          {
            "img_address": "https://gw.alipayobjects.com/zos/rmsportal/ebuQSFOLCrYqpCHmfxll.png",
            "title": "为什么这么多大企业都在做可视化页面搭建？",
            "link_address": "https://www.baidu.com"
          },
          {
            "img_address": "https://gw.alipayobjects.com/zos/rmsportal/ebuQSFOLCrYqpCHmfxll.png",
            "title": "为什么这么多大企业都在做可视化页面搭建？",
            "link_address": "https://www.baidu.com"
          }
        ]
      }
    ],
    "extends": {
      "title": "tab",
      "img": "https://two.luoqintai.cn/uploads/2021/upload_6d406052c3338d296324c81edc11afac.png"
    }
  },
  "blocktitle1": {
    "comp": "Title",
    "left_editor": "LeftPanelTitle",
    "template": "block1",
    "name": "标题",
    "style": {
      "color": "#333"
    },
    "content": "标题内容",
    "extends": {
      "title": "带装饰居中对齐标题 - 1",
      "img": "https://two.luoqintai.cn/uploads/2021/upload_7550b1069a7b541acbbc15baf17b7129.png"
    }
  },
  "dottitle1": {
    "comp": "Title",
    "left_editor": "LeftPanelTitle",
    "template": "dot1",
    "name": "标题",
    "style": {
      "color": "#333"
    },
    "content": "标题内容",
    "extends": {
      "title": "带装饰左对齐标题 - 1",
      "img": "https://two.luoqintai.cn/uploads/2021/upload_45dca79c894dfe66648ac2d8a13f8b62.png"
    }
  },
  "dottitle3": {
    "comp": "Title",
    "left_editor": "LeftPanelTitle",
    "template": "dot3",
    "name": "标题",
    "style": {
      "color": "#333"
    },
    "content": "标题内容",
    "extends": {
      "title": "带装饰左对齐标题 - 3",
      "img": "https://two.luoqintai.cn/uploads/2021/upload_395376963a2aff93ad9f9be1e14e1cd3.png"
    }
  },
  "normaltitle1": {
    "comp": "Title",
    "left_editor": "LeftPanelTitle",
    "template": "normal1",
    "name": "标题",
    "style": {
      "color": "#333"
    },
    "content": "标题内容",
    "extends": {
      "title": "普通标题 - 1",
      "img": "https://two.luoqintai.cn/uploads/2021/upload_ffa0f7eb6952d8a32b8fcbbf13809691.png"
    }
  },
  "normaltitle2": {
    "comp": "Title",
    "left_editor": "LeftPanelTitle",
    "template": "normal2",
    "name": "标题",
    "style": {
      "color": "#333"
    },
    "content": "标题内容",
    "extends": {
      "title": "普通标题 - 2",
      "img": "https://two.luoqintai.cn/uploads/2021/upload_e314ae41d0a3b94e143cffed21ccb431.png"
    }
  }
}